tensorflow-stubs/__init__.py
tensorflow-stubs/__init__.pyi
tensorflow-stubs/math/__init__.pyi
tensorflow-stubs/python/__init__.pyi
tensorflow-stubs/train/__init__.pyi
tensor_annotations_tensorflow_stubs-2.0.3.dist-info/METADATA
tensor_annotations_tensorflow_stubs-2.0.3.dist-info/WHEEL
tensor_annotations_tensorflow_stubs-2.0.3.dist-info/top_level.txt
tensor_annotations_tensorflow_stubs-2.0.3.dist-info/RECORD
