Metadata-Version: 2.1
Name: tensor-annotations-tensorflow-stubs
Version: 2.0.3
Summary: Shape-aware type stubs for TensorFlow.
Home-page: https://github.com/deepmind/tensor_annotations
Requires-Dist: tensor-annotations
